MANIFEST.in
README.md
setup.cfg
setup.py
sumo_web3d/__init__.py
sumo_web3d/scenarios.json
sumo_web3d/sumo_web3d.py
sumo_web3d.egg-info/PKG-INFO
sumo_web3d.egg-info/SOURCES.txt
sumo_web3d.egg-info/dependency_links.txt
sumo_web3d.egg-info/entry_points.txt
sumo_web3d.egg-info/requires.txt
sumo_web3d.egg-info/top_level.txt
sumo_web3d/scenarios/bologna-acosta/.gitignore
sumo_web3d/scenarios/bologna-acosta/acosta-poly.xml
sumo_web3d/scenarios/bologna-acosta/acosta.osm
sumo_web3d/scenarios/bologna-acosta/e1_output.xml
sumo_web3d/scenarios/bologna-acosta/joined.rou.xml
sumo_web3d/scenarios/bologna-acosta/joined_bus_stops.add.xml
sumo_web3d/scenarios/bologna-acosta/joined_buslanes.net.xml
sumo_web3d/scenarios/bologna-acosta/joined_busses.rou.xml
sumo_web3d/scenarios/bologna-acosta/joined_detectors.add.xml
sumo_web3d/scenarios/bologna-acosta/joined_tls.add.xml
sumo_web3d/scenarios/bologna-acosta/joined_vtypes.add.xml
sumo_web3d/scenarios/bologna-acosta/run.sumo.cfg
sumo_web3d/scenarios/bologna-acosta/tripinfos.xml
sumo_web3d/scenarios/bologna-acosta-joined/acosta-poly.xml
sumo_web3d/scenarios/bologna-acosta-joined/acosta.osm
sumo_web3d/scenarios/bologna-acosta-joined/e1_output.xml
sumo_web3d/scenarios/bologna-acosta-joined/joined.rou.xml
sumo_web3d/scenarios/bologna-acosta-joined/joined_bus_stops.add.xml
sumo_web3d/scenarios/bologna-acosta-joined/joined_buslanes.net.xml
sumo_web3d/scenarios/bologna-acosta-joined/joined_busses.rou.xml
sumo_web3d/scenarios/bologna-acosta-joined/joined_detectors.add.xml
sumo_web3d/scenarios/bologna-acosta-joined/joined_tls.add.xml
sumo_web3d/scenarios/bologna-acosta-joined/joined_vtypes.add.xml
sumo_web3d/scenarios/bologna-acosta-joined/run.sumo.cfg
sumo_web3d/scenarios/bologna-acosta-joined/tripinfos.xml
sumo_web3d/scenarios/cross3ltl/input_routes.rou.xml
sumo_web3d/scenarios/cross3ltl/net.net.xml
sumo_web3d/scenarios/cross3ltl/test.sumocfg
sumo_web3d/scenarios/downtown-toronto/lake-ontario.geojson
sumo_web3d/scenarios/downtown-toronto/toronto.bicycle.rou.alt.xml
sumo_web3d/scenarios/downtown-toronto/toronto.bicycle.rou.xml
sumo_web3d/scenarios/downtown-toronto/toronto.bicycle.trips.xml
sumo_web3d/scenarios/downtown-toronto/toronto.net.xml
