Metadata-Version: 1.0
Name: sumo-web3d
Version: 1.0.1
Summary: Web-based 3D Visualization of SUMO Traffic Simulator
Home-page: https://github.com/sidewalklabs/sumo-web3d/
Author: Sidewalk Labs
Author-email: hello@sidewalklabs.com
License: UNKNOWN
Platform: UNKNOWN
